tourbillon_celery-0.4.1-py2.7-nspkg.pth
tourbillon/celery/__init__.py
tourbillon/celery/celery2.py
tourbillon_celery-0.4.1.dist-info/DESCRIPTION.rst
tourbillon_celery-0.4.1.dist-info/METADATA
tourbillon_celery-0.4.1.dist-info/RECORD
tourbillon_celery-0.4.1.dist-info/WHEEL
tourbillon_celery-0.4.1.dist-info/metadata.json
tourbillon_celery-0.4.1.dist-info/namespace_packages.txt
tourbillon_celery-0.4.1.dist-info/top_level.txt
