Metadata-Version: 2.0
Name: tourbillon-celery
Version: 0.4.1
Summary: A tourbillon plugin for collecting metrics from celery.
Home-page: https://github.com/tourbillonpy/tourbillon-celery
Author: The Tourbillon Team
Author-email: tourbillonpy@gmail.com
License: ASF
Keywords: monitoring metrics agent influxdb celery
Platform: UNKNOWN
Classifier: Development Status :: 4 - Beta
Classifier: Intended Audience :: Developers
Classifier: Intended Audience :: System Administrators
Classifier: License :: OSI Approved :: Apache Software License
Classifier: Operating System :: POSIX :: Linux
Classifier: Programming Language :: Python
Classifier: Programming Language :: Python :: 2.7
Classifier: Programming Language :: Python :: 3.4
Classifier: Programming Language :: Python :: 3.5
Classifier: Topic :: System :: Monitoring
Requires-Dist: celery (>=3.1.8)
